zhuqiyang_mcp_dev/__init__.py
zhuqiyang_mcp_dev-0.1.0.dist-info/METADATA
zhuqiyang_mcp_dev-0.1.0.dist-info/WHEEL
zhuqiyang_mcp_dev-0.1.0.dist-info/entry_points.txt
zhuqiyang_mcp_dev-0.1.0.dist-info/RECORD
