Metadata-Version: 2.4
Name: zhuqiyang-mcp-dev
Version: 0.1.0
Summary: Add your description here
Author-email: root <qiqitao320@qq.com>
Requires-Python: >=3.13
Requires-Dist: mcp[cli]>=1.9.4
